LICENSE.TXT
README.md
setup.cfg
setup.py
protected_classification.egg-info/PKG-INFO
protected_classification.egg-info/SOURCES.txt
protected_classification.egg-info/dependency_links.txt
protected_classification.egg-info/requires.txt
protected_classification.egg-info/top_level.txt
src/__init__.py
src/analysis.py
src/experiments.py
src/protected_classification.py
src/summary.py
src/test.py
src/test_multiclass.py
src/va_bin.py