Metadata-Version: 2.1
Name: protected-classification
Version: 0.1.3
Summary: Protected Classification package
Home-page: https://github.com/ip200/protected-classification
Download-URL: https://github.com/ip200/protected-classification/archive/refs/tags/v0_1_3.tar.gz
Author: Ivan Petej
Author-email: ivan.petej@gmail.com
License: MIT
Keywords: Probabilistic classification,calibration
Classifier: Development Status :: 3 - Alpha
Classifier: Intended Audience :: Developers
Classifier: License :: OSI Approved :: MIT License
Classifier: Programming Language :: Python :: 3
License-File: LICENSE.TXT
